{
  "accepted_points": 3,
  "candidate_points": 3,
  "csv_path": "/Users/craig/ECDO/LITTORAL/outputs/per_source/day1866.csv",
  "detail": "accepted 3 point(s)",
  "finished_at": 1776991533.773796,
  "heartbeat_at": 1776991533.773796,
  "lease_key": "day1866",
  "owner": {
    "host": "Mac-Studio.local",
    "pid": 29087,
    "run_id": "29c65358d9c840d9bb152bb9816aa625"
  },
  "source_id": "day1866",
  "source_name": "day1866.pdf",
  "source_path": "/Users/craig/ECDO/LITTORAL/data/incoming/day1866.pdf",
  "stage": "completed",
  "started_at": 1776990120.9269388,
  "status": "completed",
  "summary_path": "/Users/craig/ECDO/LITTORAL/outputs/per_source/day1866.summary.md",
  "unresolved_entries": 0,
  "updated_at": 1776991533.773796
}
