{
  "accepted_points": 0,
  "candidate_points": 0,
  "csv_path": "/Users/craig/ECDO/LITTORAL/outputs/per_source/ward2023.csv",
  "detail": "accepted 0 point(s)",
  "finished_at": 1777010329.64478,
  "heartbeat_at": 1777010329.64478,
  "lease_key": "ward2023",
  "owner": {
    "host": "Mac-Studio.local",
    "pid": 29087,
    "run_id": "29c65358d9c840d9bb152bb9816aa625"
  },
  "source_id": "ward2023",
  "source_name": "ward2023.pdf",
  "source_path": "/Users/craig/ECDO/LITTORAL/data/incoming/ward2023.pdf",
  "stage": "completed",
  "started_at": 1777008425.709898,
  "status": "completed",
  "summary_path": "/Users/craig/ECDO/LITTORAL/outputs/per_source/ward2023.summary.md",
  "unresolved_entries": 1,
  "updated_at": 1777010329.64478
}
