{
  "csv_path": "/Users/craig/ECDO/LITTORAL/outputs/per_source/molodkov2002.csv",
  "detail": "cache miss; attempting extraction",
  "finished_at": null,
  "heartbeat_at": 1776977697.765897,
  "lease_key": "molodkov2002",
  "owner": {
    "host": "Mac-Studio.local",
    "pid": 14922,
    "run_id": "586ccbfd656a4ffdaa393f64f3ee5799"
  },
  "source_id": "molodkov2002",
  "source_name": "molodkov2002.pdf",
  "source_path": "/Users/craig/ECDO/LITTORAL/data/incoming/molodkov2002.pdf",
  "stage": "mineru",
  "started_at": 1776977545.647285,
  "status": "running",
  "summary_path": "/Users/craig/ECDO/LITTORAL/outputs/per_source/molodkov2002.summary.md",
  "updated_at": 1776977697.765897
}
