{
  "csv_path": "/Users/craig/ECDO/LITTORAL/outputs/per_source/zong2013.csv",
  "detail": "running deterministic and inference stages",
  "finished_at": null,
  "heartbeat_at": 1777014319.074076,
  "lease_key": "zong2013",
  "owner": {
    "host": "Mac-Studio.local",
    "pid": 69371,
    "run_id": "0b46c487f8ea44b98004b3511add45bc"
  },
  "source_id": "zong2013",
  "source_name": "zong2013.pdf",
  "source_path": "/Users/craig/ECDO/LITTORAL/data/incoming/zong2013.pdf",
  "stage": "extract",
  "started_at": 1777013486.5536609,
  "status": "running",
  "summary_path": "/Users/craig/ECDO/LITTORAL/outputs/per_source/zong2013.summary.md",
  "updated_at": 1777014319.074076
}
